pinax/__init__.py
pinax/notifications/__init__.py
pinax/notifications/admin.py
pinax/notifications/apps.py
pinax/notifications/compat.py
pinax/notifications/conf.py
pinax/notifications/engine.py
pinax/notifications/hooks.py
pinax/notifications/lockfile.py
pinax/notifications/models.py
pinax/notifications/signals.py
pinax/notifications/urls.py
pinax/notifications/utils.py
pinax/notifications/views.py
pinax/notifications/backends/__init__.py
pinax/notifications/backends/base.py
pinax/notifications/backends/email.py
pinax/notifications/locale/es_AR/LC_MESSAGES/django.po
pinax/notifications/locale/fr/LC_MESSAGES/django.mo
pinax/notifications/locale/fr/LC_MESSAGES/django.po
pinax/notifications/locale/ru/LC_MESSAGES/django.mo
pinax/notifications/locale/ru/LC_MESSAGES/django.po
pinax/notifications/management/__init__.py
pinax/notifications/management/commands/__init__.py
pinax/notifications/management/commands/emit_notices.py
pinax/notifications/migrations/0001_initial.py
pinax/notifications/migrations/0002_auto_20171003_2006.py
pinax/notifications/migrations/__init__.py
pinax/notifications/templates/pinax/notifications/base.html
pinax/notifications/templates/pinax/notifications/email_body.txt
pinax/notifications/templates/pinax/notifications/email_subject.txt
pinax/notifications/templates/pinax/notifications/full.txt
pinax/notifications/templates/pinax/notifications/notice_settings.html
pinax/notifications/templates/pinax/notifications/short.txt
pinax/notifications/tests/__init__.py
pinax/notifications/tests/models.py
pinax/notifications/tests/test_commands.py
pinax/notifications/tests/test_models.py
pinax/notifications/tests/test_views.py
pinax/notifications/tests/tests.py
pinax/notifications/tests/urls.py
pinax_notifications-5.0.3.dist-info/DESCRIPTION.rst
pinax_notifications-5.0.3.dist-info/METADATA
pinax_notifications-5.0.3.dist-info/RECORD
pinax_notifications-5.0.3.dist-info/WHEEL
pinax_notifications-5.0.3.dist-info/metadata.json
pinax_notifications-5.0.3.dist-info/top_level.txt
